LingyuQudongSheji/README.md
LingyuQudongSheji/__init__.py
LingyuQudongSheji/__main__.py
LingyuQudongSheji/file.epub
LingyuQudongSheji/index.html
LingyuQudongSheji/css/__init__.py
LingyuQudongSheji/css/annotations.css
LingyuQudongSheji/css/main.css
LingyuQudongSheji/css/normalize.css
LingyuQudongSheji/css/popup.css
LingyuQudongSheji/font/__init__.py
LingyuQudongSheji/font/fontello.eot
LingyuQudongSheji/font/fontello.svg
LingyuQudongSheji/font/fontello.ttf
LingyuQudongSheji/font/fontello.woff
LingyuQudongSheji/img/__init__.py
LingyuQudongSheji/img/annotator-glyph-sprite.png
LingyuQudongSheji/img/annotator-icon-sprite.png
LingyuQudongSheji/img/apple-touch-icon.png
LingyuQudongSheji/img/cancelfullscreen.png
LingyuQudongSheji/img/close.png
LingyuQudongSheji/img/fullscreen.png
LingyuQudongSheji/img/loader.gif
LingyuQudongSheji/img/menu-icon.png
LingyuQudongSheji/img/save.png
LingyuQudongSheji/img/saved.png
LingyuQudongSheji/img/settings-s.png
LingyuQudongSheji/img/settings.png
LingyuQudongSheji/img/star.png
LingyuQudongSheji/js/__init__.py
LingyuQudongSheji/js/epub.js
LingyuQudongSheji/js/epub.min.js
LingyuQudongSheji/js/epub.min.map
LingyuQudongSheji/js/hooks.min.js
LingyuQudongSheji/js/hooks.min.map
LingyuQudongSheji/js/reader.js
LingyuQudongSheji/js/reader.js.map
LingyuQudongSheji/js/reader.min.js
LingyuQudongSheji/js/reader.min.map
LingyuQudongSheji/js/hooks/__init__.py
LingyuQudongSheji/js/hooks/extensions/__init__.py
LingyuQudongSheji/js/hooks/extensions/highlight.js
LingyuQudongSheji/js/libs/__init__.py
LingyuQudongSheji/js/libs/jquery.min.js
LingyuQudongSheji/js/libs/localforage.min.js
LingyuQudongSheji/js/libs/screenfull.js
LingyuQudongSheji/js/libs/screenfull.min.js
LingyuQudongSheji/js/libs/zip.min.js
LingyuQudongSheji/js/plugins/__init__.py
LingyuQudongSheji/js/plugins/hypothesis.js
LingyuQudongSheji/js/plugins/search.js
lingyu_qudong_sheji-2024.3.5.0.dist-info/METADATA
lingyu_qudong_sheji-2024.3.5.0.dist-info/WHEEL
lingyu_qudong_sheji-2024.3.5.0.dist-info/entry_points.txt
lingyu_qudong_sheji-2024.3.5.0.dist-info/top_level.txt
lingyu_qudong_sheji-2024.3.5.0.dist-info/RECORD
